{
  "backdrops": {
    "Emerald": 2.68,
    "Orange": 2.7,
    "Pistachio": 2.68,
    "Silver Blue": 2.68,
    "Gunship Green": 2.68,
    "Pine Green": 2.7,
    "French Blue": 2.69,
    "Ranger Green": 2.69,
    "Burnt Sienna": 2.69,
    "Carmine": 2.79,
    "Satin Gold": 2.69,
    "Fandango": 2.68,
    "Cappuccino": 2.68,
    "Feldgrau": 2.7,
    "Pacific Cyan": 2.75,
    "Raspberry": 2.68,
    "Deep Cyan": 2.7,
    "Celtic Blue": 2.7,
    "Mexican Pink": 2.79,
    "Old Gold": 2.7,
    "Electric Indigo": 2.68,
    "Aquamarine": 2.69,
    "Carrot Juice": 2.68,
    "Chocolate": 2.68,
    "Caramel": 2.7,
    "Seal Brown": 2.69,
    "Sky Blue": 2.68,
    "Pacific Green": 2.68,
    "Dark Lilac": 2.7,
    "Moonstone": 2.68,
    "Roman Silver": 2.69,
    "Jade Green": 2.7,
    "Marine Blue": 2.7,
    "Amber": 2.68,
    "Mystic Pearl": 2.69,
    "Platinum": 2.7,
    "Mint Green": 2.7,
    "Rosewood": 2.69,
    "French Violet": 2.69,
    "English Violet": 2.69,
    "Camo Green": 2.69,
    "Indigo Dye": 2.7,
    "Cobalt Blue": 2.69,
    "Malachite": 2.68,
    "Sapphire": 2.68,
    "Strawberry": 2.7,
    "Gunmetal": 2.88,
    "Electric Purple": 2.68,
    "Pure Gold": 2.7,
    "Tactical Pine": 2.69,
    "Lemongrass": 2.68,
    "Azure Blue": 2.69,
    "Copper": 2.69,
    "Chestnut": 2.7,
    "Coral Red": 2.68,
    "Cyberpunk": 2.7,
    "Khaki Green": 2.69,
    "Desert Sand": 2.69,
    "Light Olive": 2.69,
    "Hunter Green": 2.7,
    "Steel Grey": 2.68,
    "Lavender": 2.68,
    "Navy Blue": 2.68,
    "Dark Green": 2.7,
    "Persimmon": 2.7,
    "Ivory White": 2.79,
    "Fire Engine": 2.8,
    "Turquoise": 2.73,
    "Mustard": 2.7,
    "Burgundy": 2.68,
    "Grape": 2.68,
    "Tomato": 2.69,
    "Shamrock Green": 2.7,
    "Purple": 2.7,
    "Battleship Grey": 2.71,
    "Midnight Blue": 2.856,
    "Rifle Green": 2.69,
    "Neon Blue": 2.7,
    "Onyx Black": 4.9878,
    "Black": 17.3298
  },
  "symbols": {
    "Alert Serpent": 3.44,
    "Angel": 4.0,
    "Angelic Heart": 2.87,
    "Apple": 4.0,
    "Avocado": 4.0,
    "Aztec Falcon": 3.48,
    "Ball": 4.0,
    "Balloon": 4.0,
    "Banana": 4.0,
    "Bandage": 4.28,
    "Baphomet": 4.89,
    "Bascinet": 2.93,
    "Baseball Cap": 3.75,
    "Basketball": 3.24,
    "Bee": 3.5,
    "Beer": 3.0,
    "Bishop": 4.0,
    "Blooms": 4.0,
    "Blossom": 3.5,
    "Boat": 3.33,
    "Bobby Helmet": 3.53,
    "Bone": 3.99,
    "Breeze": 3.27,
    "Bubble Tea": 2.95,
    "Bubbles": 2.99,
    "Burger": 3.78,
    "Cactus Bloom": 2.98,
    "Cactus": 2.89,
    "Cake": 3.0,
    "Calla Lily": 3.0,
    "Carambola": 3.3,
    "Carrot": 2.95,
    "Cheese": 2.95,
    "Cherry": 3.9,
    "Chest": 2.99,
    "Chick": 3.0,
    "Chili": 3.3,
    "Chocolate": 4.0,
    "Cicada": 3.49,
    "Clover": 2.94,
    "Coat of Arms": 3.07,
    "Cobra": 2.99,
    "Coffee Bean": 4.07,
    "Crescent": 3.8,
    "Cricket Helmet": 3.88,
    "Crystal": 3.42,
    "Cunning Fox": 3.75,
    "Cupid's Arrow": 4.8,
    "Cupid": 3.0,
    "Cute Bear": 3.33,
    "Cyclamen": 3.0,
    "Daisy": 3.0,
    "Dessert": 3.2,
    "Doghouse": 3.0,
    "Earth": 3.0,
    "Eye of Horus": 3.15,
    "Feather": 2.93,
    "Fenrir": 2.87,
    "Fireman Hat": 4.9,
    "Fish Skeleton": 3.4,
    "Flat Cap": 3.92,
    "Fleur-de-lis": 2.95,
    "Fluffy Wolf": 3.0,
    "Fried Egg": 3.0,
    "Fuchsia": 3.0,
    "Gentian": 4.0,
    "Gingerbread": 3.03,
    "Grape": 3.33,
    "Greek Sun": 3.36,
    "Griffon": 2.93,
    "Guitar": 2.93,
    "Hammerhead": 3.24,
    "Handcuffs": 3.49,
    "Hard Hat": 4.0,
    "Hazelnut": 3.99,
    "Heart Box": 3.1,
    "Heart Donut": 3.03,
    "Heart Lock": 12.0,
    "Heart Ring": 3.5,
    "Heart Shades": 3.13,
    "Hersir": 3.0,
    "High Hat": 3.42,
    "High Heels": 3.0,
    "Horned Helm": 3.9,
    "Horseshoe": 2.97,
    "Hourglass": 3.5,
    "Imperial Lion": 4.0,
    "Ink Pen": 3.85,
    "Iris": 3.88,
    "Iron Helmet": 3.0,
    "Jester Hat": 3.0,
    "Jewel": 3.3,
    "Key": 3.42,
    "Kite": 3.2,
    "Kitsune": 2.94,
    "Knight": 3.46,
    "Lavender": 3.5,
    "Lemon Slice": 2.9,
    "Light Bulb": 2.96,
    "Lily": 3.0,
    "Lion of Babylon": 3.49,
    "Lips": 3.0,
    "Little Cupid": 3.42,
    "Love Bell": 2.87,
    "Love Bulb": 5.0,
    "Loveberry": 2.94,
    "Lovely Kiss": 2.88,
    "Loving Heart": 4.0,
    "Mafdet": 3.0,
    "Magic Wand": 4.0,
    "Manta Ray": 3.99,
    "Maple Leaf": 8.0,
    "Maple": 2.99,
    "Money Bag": 3.98,
    "Moon Cross": 3.8,
    "Napkins": 3.2,
    "Nemean Lion": 3.1,
    "Nigiri": 4.0,
    "Obon Lantern": 2.87,
    "Oculus": 5.44,
    "Onigiri": 2.94,
    "Orchid": 3.2,
    "Origami": 3.63,
    "Ouroboros": 3.2,
    "Owl": 4.5,
    "Padlock": 2.87,
    "Panty": 3.32,
    "Patched Heart": 3.0,
    "Paw": 3.4,
    "Pigeon": 4.0,
    "Pixel Heart": 3.0,
    "Piñata": 3.48,
    "Plume": 2.87,
    "Pomegranate": 3.99,
    "Porrige": 3.78,
    "Press Hat": 3.88,
    "Pyramid": 3.69,
    "Rook": 4.0,
    "Rooster": 5.6,
    "Rose Blossom": 3.12,
    "Rose": 4.0,
    "Royal Crown": 3.07,
    "Sakura Flower": 2.96,
    "Scissors": 3.0,
    "Sea Dragon": 4.4,
    "Sea Jelly": 5.04,
    "Seahorse": 3.0,
    "Shark Knife": 3.93,
    "Shortsword": 3.66,
    "Sleepy Unicorn": 3.11,
    "Spider": 3.08,
    "Spirit Impala": 3.15,
    "Strawberry": 2.87,
    "Sun Lion": 3.15,
    "Sunflower": 4.0,
    "Teru Bōzu": 3.0,
    "Tie": 4.0,
    "Tiki Mask": 2.93,
    "Tooth": 4.3,
    "Top Hat": 3.99,
    "Toy Bucket": 3.32,
    "Tulip Bloom": 5.07,
    "Tulip": 3.5,
    "Turkey": 3.99,
    "Turtle": 3.5,
    "Twin Koi": 4.0,
    "Two Hearts": 4.0,
    "Venetian Mask": 5.11,
    "Wagasa": 2.95,
    "Water Drops": 3.8,
    "Watermelon": 2.98,
    "Wepwawet": 2.9,
    "Wine Toast": 3.0,
    "Winged Helmet": 3.1,
    "Yin-Yang": 3.0
  },
  "models": {
    "Alien Slime": 3.06,
    "Arizona": 3.0702,
    "Bag End": 2.958,
    "Biohazard": 3.0396,
    "Bitcoin": 7.803,
    "Bitter Sweet": 3.366,
    "Blueberry Hill": 3.06,
    "Cherry Top": 2.958,
    "Christmas": 2.9886,
    "Circus": 3.3354,
    "Cloud Nine": 2.8968,
    "Cream Scream": 4.8246,
    "Deep State": 3.6006,
    "Demoman": 2.9478,
    "Dracula": 3.1416,
    "Fantastic Four": 3.0396,
    "Fast Charge": 3.06,
    "First Bite": 2.8866,
    "Gummy Bears": 3.162,
    "Half-Life": 3.0498,
    "Hawaii": 2.907,
    "Heaven Seven": 5.1,
    "Hellspawn": 3.4578,
    "High Five": 3.0498,
    "Honey Bee": 3.264,
    "Jolly Roger": 3.315,
    "Maneki Neko": 5.6916,
    "March Eight": 3.06,
    "Minion": 9.792,
    "Ogre Snack": 3.5598,
    "Paradise": 3.366,
    "Poopy Pie": 2.8866,
    "Resistance": 7.9764,
    "Rising Dead": 2.856,
    "Six Senses": 3.0498,
    "Spiritwood": 2.8968,
    "Sponge Duck": 3.4476,
    "Stardust": 3.06,
    "Starfish": 3.315,
    "Sugar Daddy": 3.6108,
    "Sweetheart": 5.9976,
    "Tarot Cards": 3.0498,
    "Toncoin": 3.213,
    "Triple Treat": 2.856,
    "Trippy": 3.0192,
    "Trump Cake": 3.3558,
    "Two Sweet!": 2.8662,
    "Unicorn": 3.162,
    "Wasteland": 2.856,
    "Zero Sugar": 2.8662
  },
  "last_updated": 1784563791
}