{
  "backdrops": {
    "Strawberry": 2.46,
    "Orange": 2.44,
    "Khaki Green": 2.45,
    "Battleship Grey": 2.45,
    "Pistachio": 2.47,
    "Lavender": 2.41,
    "Pacific Cyan": 2.42,
    "Silver Blue": 2.4,
    "Aquamarine": 2.46,
    "Coral Red": 2.47,
    "Purple": 2.42,
    "Moonstone": 2.46,
    "Hunter Green": 2.41,
    "Ivory White": 2.42,
    "Raspberry": 2.43,
    "Shamrock Green": 2.46,
    "Chocolate": 2.39,
    "Pacific Green": 2.4,
    "Rosewood": 2.45,
    "Mint Green": 2.44,
    "Electric Indigo": 2.45,
    "Turquoise": 2.43,
    "Sky Blue": 2.44,
    "English Violet": 2.43,
    "Azure Blue": 2.4,
    "Roman Silver": 2.42,
    "Indigo Dye": 2.45,
    "Desert Sand": 2.4,
    "Chestnut": 2.46,
    "Neon Blue": 2.47,
    "Copper": 2.46,
    "Cobalt Blue": 2.43,
    "Electric Purple": 2.46,
    "Pine Green": 2.43,
    "French Blue": 2.39,
    "Persimmon": 2.46,
    "Jade Green": 2.45,
    "Dark Lilac": 2.42,
    "Midnight Blue": 10.0,
    "Burgundy": 2.45,
    "Cyberpunk": 2.45,
    "Emerald": 2.46,
    "Caramel": 2.42,
    "Sapphire": 2.38,
    "Malachite": 2.41,
    "Pure Gold": 2.41,
    "Grape": 2.44,
    "Lemongrass": 2.46,
    "Satin Gold": 2.41,
    "Cappuccino": 2.46,
    "Amber": 2.42,
    "Platinum": 2.39,
    "Light Olive": 2.46,
    "Steel Grey": 2.46,
    "Navy Blue": 2.46,
    "Carrot Juice": 2.43,
    "Fandango": 2.43,
    "Mystic Pearl": 2.42,
    "Black": 32.1,
    "Onyx Black": 13.0
  },
  "symbols": {
    "Acorn": 4.8,
    "Alarm": 4.6,
    "Alkonost": 5.1,
    "Anchor": 6.0,
    "Autumn Leaves": 4.24,
    "Axe": 7.2,
    "Bandage": 4.3,
    "Baphomet": 4.3,
    "Black Widow": 6.0,
    "Blood Drop": 4.64,
    "Bloody Axe": 4.23,
    "Bottlenose": 6.49,
    "Bow Tie": 18.0,
    "Brain": 4.6,
    "Bubbles": 6.0,
    "Bull of Heaven": 6.9,
    "Bunny": 10.0,
    "Cactus": 4.5,
    "Calm Wolf": 7.5,
    "Candle": 4.5,
    "Car": 7.89,
    "Cash": 5.0,
    "Cauldron": 4.45,
    "Chest": 5.0,
    "Chili Pepper": 4.3,
    "Cobra": 6.0,
    "Coffin": 5.5,
    "Conch": 6.0,
    "Crow": 4.7,
    "Crusader": 4.4,
    "Crystal Ball": 4.5,
    "Doberman": 5.0,
    "Dolphin": 15.0,
    "Dragonfly": 5.0,
    "Eagle": 19.99,
    "Eggplant": 5.0,
    "Elephant": 6.99,
    "Evil Pumpkin": 4.6,
    "Eyeball": 4.3,
    "Fehu Rune": 4.72,
    "Firebird": 4.65,
    "Fish Skeleton": 4.29,
    "Fish": 7.5,
    "Flipper": 4.4,
    "Flower Cross": 6.0,
    "Flower Tulip": 4.6,
    "Flying Witch": 5.0,
    "Gamepad": 4.23,
    "Gem": 8.0,
    "Genie Lamp": 4.3,
    "Ghost": 4.23,
    "Gift Box": 4.7,
    "Glasses": 9.5,
    "Gold": 4.5,
    "Gravestone": 4.7,
    "Grim Reaper": 4.8,
    "Half Moon": 4.23,
    "Hammerhead": 8.0,
    "Hand of God": 4.3,
    "Happy Smile": 5.0,
    "Hedgehog": 5.0,
    "Hippo": 10.0,
    "Human Scull": 5.0,
    "Illuminati": 5.0,
    "Inguz Rune": 4.7,
    "Jaws": 5.5,
    "Jellyfish": 5.0,
    "Jumbo Pencil": 4.5,
    "Koala": 4.7,
    "Ladybug": 7.88,
    "Leaf": 7.0,
    "Lily": 9.0,
    "Lollipop": 5.0,
    "Love Letter": 6.8,
    "Lovely Kiss": 4.3,
    "Mafdet": 4.8,
    "Magic Wand": 4.3,
    "Mannaz Rune": 13.0,
    "Maple": 5.2,
    "Mask": 5.0,
    "Moon": 4.3,
    "Moose Head": 5.7,
    "Mountain Goat": 6.85,
    "Mountain Lion": 5.5,
    "Musical Note": 8.0,
    "Nice Ghost": 4.3,
    "Night Bats": 4.5,
    "Oak Leaf": 4.7,
    "Okami Wolf": 8.0,
    "Owl": 12.0,
    "Oxen of Fire": 4.3,
    "Paw": 9.8,
    "Pickaxe": 4.38,
    "Pineapple": 5.5,
    "Pizza Slice": 9.0,
    "Planet": 5.0,
    "Plume": 7.1,
    "Poison Drop": 4.4,
    "Pomegranate": 20.0,
    "Potion": 4.8,
    "Pyramid": 4.34,
    "Rain Drop": 6.0,
    "Red Deer": 5.0,
    "Rhino Warrior": 5.0,
    "Rook": 4.7,
    "Royal Crown": 12.65,
    "Sauron": 4.3,
    "Scarab": 4.8,
    "Scarecrow": 4.3,
    "Scorpion": 5.5,
    "Severed Hand": 4.6,
    "Sharp Sword": 6.1,
    "Skull": 4.5,
    "Smartphone": 5.0,
    "Sparks": 10.0,
    "Spider Web": 5.0,
    "Spooky Cat": 4.23,
    "Star": 4.4,
    "Strawberry": 7.0,
    "Sunflower": 4.5,
    "Toilet Paper": 15.0,
    "Tooth": 4.28,
    "Top Hat": 7.06,
    "Totem Bear": 4.9,
    "Toy Bucket": 5.0,
    "Treats": 4.35,
    "Tribal Shield": 6.39,
    "Turtle": 4.85,
    "Unicorn": 4.27,
    "Venetian Mask": 6.0,
    "Viking": 4.5,
    "Voodoo Doll": 7.8,
    "Witch’s Hat": 5.0,
    "Wreath": 5.99,
    "Yogi Shaman": 4.88
  },
  "models": {
    "Baphomet": 9.48,
    "Blue Beam": 4.38,
    "Blue Steel": 4.3,
    "Bronze Rose": 4.4,
    "Bubble Bath": 12.31,
    "Burnt Amber": 4.28,
    "Candyman": 6.0,
    "Carnation": 4.59,
    "Cherry Burn": 9.89,
    "Citrus Burst": 4.25,
    "Coastal Cove": 4.45,
    "Cool Metal": 4.49,
    "Cranberry": 4.4,
    "Cult Candle": 4.5,
    "Dark Desire": 5.7,
    "Deep Sea": 4.25,
    "Dreamscape": 4.3,
    "Ephemeral": 4.65,
    "Evening Star": 4.25,
    "First Dawn": 4.28,
    "Floral Scent": 4.7,
    "Frosted Glass": 4.4,
    "Gold Stars": 4.39,
    "Gradient Wax": 4.4,
    "Gruyere": 4.5,
    "Half Moon": 4.82,
    "Healing Mist": 6.5,
    "Honeycomb": 4.3,
    "Horoscope": 4.95,
    "Hot Cocoa": 6.3,
    "Hot Emerald": 4.33,
    "Hot Kiss": 7.6,
    "Hydrangea": 4.52,
    "Iceberg": 4.5,
    "Indiglow": 4.94,
    "Jasmine": 4.44,
    "Krakatoa": 5.0,
    "Late Dusk": 4.59,
    "Little Star": 5.7,
    "Love Dreams": 4.5,
    "Mermaid": 4.29,
    "Mirkwood": 4.95,
    "My Precious": 5.0,
    "Neroli Noir": 6.99,
    "Pearl Clam": 6.99,
    "Pinstripe": 4.33,
    "Poison Ivy": 4.39,
    "Pop Art": 4.31,
    "Proposal": 7.29,
    "Purple Wave": 4.26,
    "Rainbow": 4.44,
    "Rare Jewels": 8.49,
    "Red Melter": 4.59,
    "Rose Tea": 5.5,
    "Sacred Lotus": 10.0,
    "Satin Bow": 8.1,
    "Saturated": 4.58,
    "Sequin": 6.63,
    "Serenity": 4.24,
    "Silver Spark": 5.6,
    "Snake Skin": 8.9,
    "Spiced Apple": 4.3,
    "Spring Bloom": 4.7,
    "Sugar Skull": 4.49,
    "Sunrise": 4.25,
    "Supernova": 6.09,
    "Thick Honey": 4.28,
    "Tortuga": 4.34,
    "Toxic Smoke": 4.35,
    "Twilight": 5.5,
    "Two-Tone": 4.29,
    "Unicorn": 4.39,
    "Vanilla Oasis": 5.69,
    "Warm Embrace": 4.25,
    "White Ash": 6.0,
    "Wildflowers": 6.3,
    "Winter Mist": 5.0,
    "Witch’s Candle": 7.9,
    "Wolfsbane": 4.67,
    "Yellow Gold": 4.34
  },
  "last_updated": 1782197032
}