{
  "backdrops": {
    "Electric Purple": 2.5,
    "Lemongrass": 2.5,
    "Ivory White": 2.5,
    "Tomato": 2.5,
    "Satin Gold": 2.51,
    "Amber": 2.5,
    "Chocolate": 2.5,
    "Mexican Pink": 2.5,
    "French Violet": 2.5,
    "Emerald": 2.5,
    "Pure Gold": 2.5,
    "Jade Green": 2.5,
    "Gunmetal": 2.6,
    "Celtic Blue": 2.5,
    "Azure Blue": 2.5,
    "Burgundy": 2.49,
    "Purple": 2.5,
    "Light Olive": 2.5,
    "Mystic Pearl": 2.5,
    "Fire Engine": 2.49,
    "Pacific Green": 2.5,
    "Persimmon": 2.5,
    "Roman Silver": 2.5,
    "Seal Brown": 2.5,
    "Copper": 2.5,
    "Ranger Green": 2.5,
    "Camo Green": 2.49,
    "Navy Blue": 2.5,
    "Rosewood": 2.48,
    "Mustard": 2.51,
    "Lavender": 2.5,
    "Mint Green": 2.5,
    "Battleship Grey": 2.51,
    "Shamrock Green": 2.5,
    "Hunter Green": 2.53,
    "French Blue": 2.49,
    "Marine Blue": 2.5,
    "Tactical Pine": 2.5,
    "Gunship Green": 2.49,
    "Old Gold": 2.5,
    "Carrot Juice": 2.5,
    "Raspberry": 2.52,
    "Fandango": 2.59,
    "Steel Grey": 2.5,
    "Cobalt Blue": 2.5,
    "Strawberry": 2.5,
    "Moonstone": 2.5,
    "English Violet": 2.49,
    "Grape": 2.5,
    "Khaki Green": 2.5,
    "Cappuccino": 2.5,
    "Chestnut": 2.5,
    "Malachite": 2.5,
    "Pine Green": 2.5,
    "Cyberpunk": 2.5,
    "Caramel": 2.5,
    "Pistachio": 2.49,
    "Feldgrau": 2.5,
    "Sky Blue": 2.49,
    "Aquamarine": 2.5,
    "Dark Green": 2.51,
    "Dark Lilac": 2.5,
    "Coral Red": 2.5,
    "Sapphire": 2.5,
    "Burnt Sienna": 2.51,
    "Electric Indigo": 2.5,
    "Desert Sand": 2.5,
    "Indigo Dye": 2.5,
    "Neon Blue": 2.5,
    "Deep Cyan": 2.49,
    "Platinum": 2.52,
    "Rifle Green": 2.5,
    "Midnight Blue": 9.98,
    "Carmine": 2.52,
    "Silver Blue": 2.5,
    "Orange": 2.49,
    "Turquoise": 2.5,
    "Pacific Cyan": 2.5,
    "Black": 40.0,
    "Onyx Black": 14.5
  },
  "symbols": {
    "Spider": 7.65,
    "Pumpkin Coach": 9.4,
    "Porrige": 8.4,
    "Ace Of Hearts": 10.0,
    "Alert Serpent": 9.99,
    "Alkonost": 10.0,
    "All-Seeing Eye": 15.85,
    "Amour Scoops": 10.0,
    "Anchor": 15.84,
    "Angel": 8.04,
    "Anthurium": 9.99,
    "Apple": 16.41,
    "Arcane Mirror": 11.0,
    "Astronaut": 10.0,
    "Balloon": 8.95,
    "Banana": 15.0,
    "Bandage": 15.0,
    "Bascinet": 45.0,
    "Baseball Cap": 9.0,
    "Beer": 8.48,
    "Bellflower": 8.5,
    "Bottlenose": 9.49,
    "Bougainvillea": 23.5,
    "Bouquet": 10.0,
    "Bowler Hat": 8.13,
    "Brain": 8.7,
    "Broken Heart": 9.0,
    "Bug": 21.0,
    "Bull of Heaven": 10.0,
    "Butterfly": 19.0,
    "Calendula": 20.0,
    "Celtic Cross": 30.0,
    "Champagne": 9.0,
    "Chrysanthe": 21.9,
    "Clematis": 8.05,
    "Clover": 8.64,
    "Crown": 11.0,
    "Crystal Ball": 16.6,
    "Cupcake": 15.0,
    "Cupid Archer": 13.9,
    "Cupid's Arrow": 10.0,
    "Cupid": 9.0,
    "Daisy": 28.0,
    "Dandelion": 22.0,
    "Deerstalker": 13.43,
    "Diamond": 12.1,
    "Doghouse": 9.5,
    "Donut": 8.5,
    "Double Axe": 15.0,
    "Dragonfly": 18.88,
    "Earflap Hat": 14.0,
    "Easter Bunny": 11.99,
    "February 14": 10.0,
    "Firebird": 13.0,
    "Fishing Hook": 20.0,
    "Flower Cross": 20.3,
    "French Fries": 9.51,
    "Fuchsia": 22.0,
    "Galaxy": 8.13,
    "Gentian": 10.0,
    "Ghost": 19.9,
    "Gift": 10.0,
    "Greek Helmet": 8.39,
    "Grenade": 17.61,
    "Griffon": 15.0,
    "Gua Pi Mao": 13.0,
    "Hammerhead": 20.0,
    "Hand of God": 9.0,
    "Hazelnut": 10.0,
    "Headband": 20.99,
    "Heart Box": 24.0,
    "Heart Ring": 19.99,
    "Hearts": 25.0,
    "Heraldic Lily": 9.5,
    "Hersir": 9.91,
    "Holy Grail": 8.99,
    "Horseshoe": 10.0,
    "Hot Matcha": 14.0,
    "Inca Sun": 15.5,
    "Key": 9.0,
    "Kitsune Mask": 9.4,
    "Knight": 10.0,
    "Koala": 13.0,
    "La Corona": 8.95,
    "Lavender": 11.72,
    "Like Button": 9.0,
    "Lily": 10.0,
    "Lion Head": 21.0,
    "Little Cupid": 8.44,
    "Love Bell": 24.8,
    "Love Daisy": 8.7,
    "Love Potion": 9.8,
    "Love Scene": 12.0,
    "Lovely Bra": 10.0,
    "Lovely Key": 12.0,
    "Lovely Kiss": 10.9,
    "Loving Heart": 10.5,
    "Mafdet": 10.0,
    "Magic Hat": 9.5,
    "Magic Wand": 10.4,
    "Maple": 14.0,
    "Mayan Moth": 8.13,
    "Meat Leg": 10.0,
    "Melon": 9.4,
    "Mining Helmet": 12.0,
    "Monstera": 8.02,
    "Moon Face": 8.65,
    "Moon": 10.0,
    "Morgenstern": 9.55,
    "Moto Helmet": 13.0,
    "Mountain Goat": 9.0,
    "Mountain Lion": 8.49,
    "Muffin": 9.61,
    "Musical Note": 30.0,
    "Mustache": 79.9,
    "Napkins": 11.02,
    "Neko Mask": 12.0,
    "Nigiri": 10.0,
    "Obon Lantern": 13.7,
    "Octopus": 20.5,
    "Old Candle": 9.5,
    "Oxen of Fire": 18.5,
    "Paper Crane": 11.5,
    "Patched Heart": 22.0,
    "PC Mouse": 17.0,
    "Pencil": 12.0,
    "Plum": 8.05,
    "Plumeria": 9.0,
    "Polar Bear": 11.73,
    "Press Hat": 12.0,
    "Pussy Willow": 10.0,
    "Puzzle": 14.9,
    "Pyramid": 8.66,
    "Rabbit Mask": 8.2,
    "Rain Drop": 20.0,
    "Ramen": 20.97,
    "Romantic Cake": 11.73,
    "Rook": 8.09,
    "Rose Bud": 8.7,
    "Sakura Flower": 11.0,
    "Sakura": 13.5,
    "Sauron": 12.5,
    "Shinto Shrine": 13.0,
    "Shiny Heart": 18.0,
    "Shooting Star": 14.0,
    "Shortsword": 23.8,
    "Shuriken": 8.25,
    "Snail": 12.0,
    "Snowdrop": 19.6,
    "Straw Hat": 10.0,
    "Strawberry": 11.0,
    "Takoyaki": 15.0,
    "Teddy Bear": 13.0,
    "Teru Bōzu": 8.7,
    "Tie": 26.0,
    "Toilet Paper": 9.0,
    "Tongue": 16.0,
    "Totem Bear": 17.1,
    "Tree of Life": 14.98,
    "Tricorne": 8.01,
    "Trinity Knot": 12.0,
    "Tulip Bloom": 12.5,
    "Turtle": 13.7,
    "Twin Koi": 8.7,
    "Twin Peaks": 8.4,
    "Wagasa": 15.0,
    "War Tiger": 10.0,
    "Wasp": 8.4,
    "Winged Helmet": 12.98,
    "Wise Raven": 10.0,
    "Worker Ant": 299.0
  },
  "models": {
    "Art Deco": 8.7,
    "Blue Suede": 8.32,
    "Cherry": 10.0,
    "Chess Set": 30.0,
    "Choco Mint": 11.99,
    "Christmas": 8.19,
    "Clear Case": 9.0,
    "Clockwork": 8.3,
    "Crime Scene": 9.98,
    "First Aid": 8.0,
    "Flash Tattoo": 9.98,
    "Froggie": 13.0,
    "Fuse Box": 7.9,
    "Gold Dust": 8.0,
    "Golden Bear": 8.9,
    "Gothic": 9.31,
    "Green Apple": 9.13,
    "Hitman": 65.0,
    "Hollywood": 8.8,
    "Inbox": 11.0,
    "Infinity": 8.4,
    "Kiss Emoji": 17.9,
    "Kitten": 22.0,
    "Knitting Kit": 7.86,
    "Lavender": 8.13,
    "Minnie": 18.99,
    "Molten Core": 8.82,
    "Moonlight": 11.9,
    "Nikola Tesla": 8.07,
    "Outline": 8.88,
    "Pizza": 13.98,
    "Polka Dots": 9.99,
    "Pop Art": 9.0,
    "Prestige": 8.78,
    "Red Velvet": 19.0,
    "Redshift": 13.0,
    "Resistance": 24.0,
    "Sakura": 8.53,
    "Silver Blue": 7.98,
    "Snow Queen": 9.0,
    "Snow White": 8.99,
    "Summer": 11.8,
    "Tartan": 8.31,
    "Tiffany": 9.0,
    "Toncoin": 31.3,
    "Top Brass": 8.1,
    "Traveler": 8.3,
    "Vampire": 13.39,
    "Vibrant": 8.22,
    "White Gold": 8.9
  },
  "last_updated": 1782681412
}