{
  "backdrops": {
    "Navy Blue": 2.58,
    "Lemongrass": 2.62,
    "Moonstone": 2.64,
    "Seal Brown": 2.64,
    "Satin Gold": 2.59,
    "Caramel": 2.59,
    "Battleship Grey": 2.62,
    "Purple": 2.62,
    "French Violet": 2.61,
    "French Blue": 2.68,
    "Jade Green": 2.62,
    "Copper": 2.59,
    "Electric Indigo": 2.59,
    "Sky Blue": 2.59,
    "Fandango": 2.59,
    "Desert Sand": 2.62,
    "Gunmetal": 2.69,
    "Carrot Juice": 2.62,
    "Coral Red": 2.59,
    "Strawberry": 2.62,
    "Pine Green": 2.61,
    "Cyberpunk": 2.64,
    "Chestnut": 2.62,
    "Fire Engine": 2.62,
    "Rifle Green": 2.61,
    "Feldgrau": 2.61,
    "Hunter Green": 2.61,
    "Cobalt Blue": 2.59,
    "Chocolate": 2.59,
    "Tactical Pine": 2.61,
    "Mexican Pink": 2.6,
    "Amber": 2.62,
    "Pistachio": 2.61,
    "Celtic Blue": 2.61,
    "Azure Blue": 2.59,
    "Burnt Sienna": 2.65,
    "Emerald": 2.59,
    "Mint Green": 2.59,
    "Tomato": 2.64,
    "Orange": 2.59,
    "Electric Purple": 2.66,
    "Platinum": 2.65,
    "Cappuccino": 2.61,
    "Indigo Dye": 2.59,
    "Roman Silver": 2.61,
    "Turquoise": 2.61,
    "Camo Green": 2.59,
    "Pacific Cyan": 2.6,
    "Light Olive": 2.59,
    "Khaki Green": 2.59,
    "Persimmon": 2.63,
    "Lavender": 2.61,
    "Steel Grey": 2.58,
    "Burgundy": 2.59,
    "Neon Blue": 2.62,
    "Sapphire": 2.59,
    "Shamrock Green": 2.59,
    "Pure Gold": 2.59,
    "Ivory White": 2.59,
    "Carmine": 2.59,
    "Rosewood": 2.63,
    "Deep Cyan": 2.6,
    "English Violet": 2.59,
    "Grape": 2.6,
    "Aquamarine": 2.6,
    "Marine Blue": 2.62,
    "Silver Blue": 2.59,
    "Midnight Blue": 20.0,
    "Ranger Green": 2.59,
    "Mustard": 2.59,
    "Old Gold": 2.63,
    "Malachite": 2.65,
    "Mystic Pearl": 2.61,
    "Raspberry": 2.63,
    "Pacific Green": 2.64,
    "Gunship Green": 2.59,
    "Dark Green": 2.62,
    "Dark Lilac": 2.61,
    "Black": 68.9,
    "Onyx Black": 29.0
  },
  "symbols": {},
  "models": {
    "April": 18.0,
    "Asmodea": 30.0,
    "Aurora": 20.0,
    "Cinderella": 39.9,
    "Companion": 17.4,
    "Coquette": 16.5,
    "Cowgirl": 19.0,
    "Crypto Queen": 55.0,
    "Diaethria": 15.9,
    "Diva": 50.0,
    "Eooxy": 16.0,
    "Fergie": 16.43,
    "Fluffy Cloud": 35.0,
    "Forget-Me-Not": 17.5,
    "Fortuna": 63.9,
    "Free Spirit": 16.0,
    "Frozen": 17.0,
    "Glam Doll": 23.6,
    "Glossy": 29.99,
    "Good Fairy": 20.0,
    "Graphium": 18.99,
    "Heartbeat": 20.0,
    "Heliconius": 27.0,
    "Hellcat": 71.0,
    "Jasmine": 17.3,
    "Jester": 23.0,
    "Ladybug": 16.2,
    "Leopard": 19.0,
    "Lost World": 18.93,
    "Machaon": 17.0,
    "Mermaid": 20.0,
    "Mistress": 17.99,
    "Mystery": 20.0,
    "Phantom Blush": 17.0,
    "Pixie Dust": 20.0,
    "Poison Ivy": 16.5,
    "Queen Bee": 16.0,
    "Rebel": 15.91,
    "Rendezvous": 20.0,
    "Rosaria": 16.0,
    "Rosy Moth": 18.0,
    "Serpent": 18.0,
    "Shining Star": 16.0,
    "Snow White": 15.9,
    "Spidergirl": 33.0,
    "Teardrops": 17.0,
    "Tinker": 18.0,
    "Vogue": 27.9,
    "White Rose": 27.99,
    "Wild Cherry": 19.0
  },
  "last_updated": 1783159931
}