{
  "backdrops": {
    "Navy Blue": 2.48,
    "Lemongrass": 2.49,
    "Moonstone": 2.47,
    "Seal Brown": 2.48,
    "Satin Gold": 2.47,
    "Caramel": 2.48,
    "Battleship Grey": 2.48,
    "Purple": 2.47,
    "French Violet": 2.48,
    "French Blue": 2.48,
    "Jade Green": 2.47,
    "Copper": 2.48,
    "Electric Indigo": 2.5,
    "Sky Blue": 2.48,
    "Fandango": 2.5,
    "Desert Sand": 2.48,
    "Gunmetal": 2.51,
    "Carrot Juice": 2.47,
    "Coral Red": 2.48,
    "Strawberry": 2.49,
    "Pine Green": 2.48,
    "Cyberpunk": 2.51,
    "Chestnut": 2.49,
    "Fire Engine": 2.54,
    "Rifle Green": 2.48,
    "Feldgrau": 2.49,
    "Hunter Green": 2.47,
    "Cobalt Blue": 2.48,
    "Chocolate": 2.48,
    "Tactical Pine": 2.48,
    "Mexican Pink": 2.48,
    "Amber": 2.47,
    "Pistachio": 2.49,
    "Celtic Blue": 2.47,
    "Azure Blue": 2.49,
    "Burnt Sienna": 2.49,
    "Emerald": 2.5,
    "Mint Green": 2.48,
    "Tomato": 2.48,
    "Orange": 2.48,
    "Electric Purple": 2.48,
    "Platinum": 2.48,
    "Cappuccino": 2.48,
    "Indigo Dye": 2.48,
    "Roman Silver": 2.49,
    "Turquoise": 2.47,
    "Camo Green": 2.49,
    "Pacific Cyan": 2.49,
    "Light Olive": 2.47,
    "Khaki Green": 2.48,
    "Persimmon": 2.48,
    "Lavender": 2.48,
    "Steel Grey": 2.48,
    "Burgundy": 2.47,
    "Neon Blue": 2.5,
    "Sapphire": 2.48,
    "Shamrock Green": 2.47,
    "Pure Gold": 2.49,
    "Ivory White": 2.5,
    "Carmine": 2.6,
    "Rosewood": 2.49,
    "Deep Cyan": 2.47,
    "English Violet": 2.48,
    "Grape": 2.47,
    "Aquamarine": 2.47,
    "Marine Blue": 2.48,
    "Silver Blue": 2.47,
    "Midnight Blue": 18.0,
    "Ranger Green": 2.49,
    "Mustard": 2.48,
    "Old Gold": 2.48,
    "Malachite": 2.48,
    "Mystic Pearl": 2.48,
    "Raspberry": 2.49,
    "Pacific Green": 2.48,
    "Gunship Green": 2.48,
    "Dark Green": 2.47,
    "Dark Lilac": 2.49,
    "Black": 70.0,
    "Onyx Black": 25.0
  },
  "symbols": {},
  "models": {
    "April": 13.39,
    "Asmodea": 19.78,
    "Aurora": 13.41,
    "Cinderella": 34.0,
    "Companion": 13.35,
    "Coquette": 15.0,
    "Cowgirl": 14.0,
    "Crypto Queen": 49.0,
    "Diaethria": 13.32,
    "Diva": 19.7,
    "Eooxy": 13.33,
    "Fergie": 13.31,
    "Fluffy Cloud": 40.0,
    "Forget-Me-Not": 17.67,
    "Fortuna": 54.0,
    "Free Spirit": 13.99,
    "Frozen": 17.0,
    "Glam Doll": 16.69,
    "Glossy": 17.0,
    "Good Fairy": 16.99,
    "Graphium": 15.15,
    "Heartbeat": 24.0,
    "Heliconius": 13.8,
    "Hellcat": 68.0,
    "Jasmine": 13.33,
    "Jester": 14.25,
    "Ladybug": 16.99,
    "Leopard": 13.75,
    "Lost World": 20.0,
    "Machaon": 13.39,
    "Mermaid": 15.0,
    "Mistress": 14.0,
    "Mystery": 13.32,
    "Phantom Blush": 24.99,
    "Pixie Dust": 17.0,
    "Poison Ivy": 14.99,
    "Queen Bee": 13.78,
    "Rebel": 13.32,
    "Rendezvous": 19.0,
    "Rosaria": 16.0,
    "Rosy Moth": 36.73,
    "Serpent": 18.0,
    "Shining Star": 14.9,
    "Snow White": 13.32,
    "Spidergirl": 30.0,
    "Teardrops": 17.0,
    "Tinker": 13.93,
    "Vogue": 27.0,
    "White Rose": 27.0,
    "Wild Cherry": 17.0
  },
  "last_updated": 1782030963
}