{
  "backdrops": {
    "Lemongrass": 2.57,
    "Mystic Pearl": 2.57,
    "Steel Grey": 2.52,
    "Hunter Green": 2.49,
    "Moonstone": 2.55,
    "Orange": 2.53,
    "Roman Silver": 2.51,
    "Chestnut": 2.59,
    "Pacific Green": 2.56,
    "Pine Green": 2.56,
    "English Violet": 2.5,
    "Jade Green": 2.58,
    "Dark Lilac": 2.54,
    "Platinum": 2.55,
    "Sapphire": 2.58,
    "Chocolate": 2.53,
    "Emerald": 2.56,
    "Copper": 2.57,
    "Midnight Blue": 35.55,
    "Malachite": 2.56,
    "Rosewood": 2.53,
    "Ivory White": 2.59,
    "Raspberry": 2.57,
    "Coral Red": 2.54,
    "Turquoise": 2.54,
    "Indigo Dye": 2.55,
    "Light Olive": 2.53,
    "Cappuccino": 2.53,
    "Persimmon": 2.57,
    "Neon Blue": 2.57,
    "Pistachio": 2.56,
    "Khaki Green": 2.57,
    "Purple": 2.57,
    "Shamrock Green": 2.57,
    "Sky Blue": 2.57,
    "Caramel": 2.54,
    "Amber": 2.57,
    "Azure Blue": 2.57,
    "Silver Blue": 2.58,
    "Aquamarine": 2.57,
    "Desert Sand": 2.57,
    "Strawberry": 2.52,
    "Electric Purple": 2.59,
    "Fandango": 2.54,
    "Burgundy": 2.57,
    "Electric Indigo": 2.53,
    "Grape": 2.57,
    "Battleship Grey": 2.57,
    "Mint Green": 2.57,
    "Lavender": 2.52,
    "Carrot Juice": 2.57,
    "Cyberpunk": 2.57,
    "Pacific Cyan": 2.57,
    "Navy Blue": 2.53,
    "French Blue": 2.51,
    "Cobalt Blue": 2.54,
    "Pure Gold": 2.52,
    "Satin Gold": 2.53,
    "Black": 114.0,
    "Onyx Black": 79.0
  },
  "symbols": {
    "Champagne": 25.26,
    "Genie Lamp": 25.6,
    "Hammerhead": 29.0,
    "Magic Hat": 58.0,
    "Sea Horse": 84.39,
    "Tree of Life": 25.96,
    "Yin-Yang": 79.9,
    "Axe": 27.64,
    "Tiki Mask": 27.0,
    "Rainbow": 25.76,
    "Fish": 105.01,
    "Pearl": 28.5,
    "Shortsword": 26.61,
    "Chick": 44.99,
    "Ace Of Hearts": 35.0,
    "Acorn": 32.0,
    "Alert Serpent": 60.0,
    "All-Seeing Eye": 30.0,
    "Amour Scoops": 33.0,
    "Anchor": 35.0,
    "Angel": 28.8,
    "Anubis": 42.0,
    "Apple": 35.0,
    "Arabian Horse": 29.99,
    "Aubergine": 40.0,
    "Aztec Falcon": 50.0,
    "Balloon": 45.0,
    "Bamboo": 29.0,
    "Bastet": 45.0,
    "Birthday Cake": 99.0,
    "Bishop": 45.0,
    "Black Cat": 39.95,
    "Blossom": 35.5,
    "Bone": 88.0,
    "Bottle": 70.0,
    "Breeze": 38.99,
    "Broken Heart": 37.99,
    "Bubbles": 31.0,
    "Bull of Heaven": 40.0,
    "Bunny Ears": 60.0,
    "Bunny": 34.5,
    "Cake": 63.0,
    "Calm Wolf": 36.5,
    "Candle": 38.0,
    "Cap": 25.97,
    "Car": 26.48,
    "Carambola": 35.0,
    "Cash": 32.49,
    "Celtic Cross": 30.0,
    "Celtic Wolf": 34.0,
    "Cheese": 40.0,
    "Cherry": 38.0,
    "Chest": 32.99,
    "Chili": 25.98,
    "Coat of Arms": 32.92,
    "Cobra": 39.99,
    "Cocktail": 30.0,
    "Coconut": 38.0,
    "Coin Purse": 45.0,
    "Coin": 25.97,
    "Corn": 40.0,
    "Cow Skull": 39.0,
    "Crab": 109.5,
    "Crescent": 50.0,
    "Crown": 37.95,
    "Crusader Cross": 26.9,
    "Crusader": 38.0,
    "Crystal": 30.0,
    "Cupid": 36.0,
    "Cupid’s Arrow": 59.0,
    "Cute Bear": 31.58,
    "Dagger": 60.0,
    "Dessert": 38.0,
    "Diamond": 30.0,
    "Dice": 55.0,
    "Divine Falcon": 33.39,
    "Doberman": 37.0,
    "Double Axe": 35.0,
    "Double Bed": 40.0,
    "Drug": 64.0,
    "Egg": 39.8,
    "Eggplant": 40.0,
    "Evil Dragon": 35.0,
    "Eye of Horus": 33.0,
    "Fehu Rune": 55.0,
    "Fire": 28.8,
    "Firebird": 29.5,
    "Fish Skeleton": 33.0,
    "Flaming Heart": 28.78,
    "Fleur-de-lis": 30.5,
    "Flower Cross": 34.95,
    "Flower Sun": 150.0,
    "Flower Tulip": 35.99,
    "Flower": 40.0,
    "Flying Dragon": 32.0,
    "French Fries": 38.0,
    "Full Moon": 38.0,
    "Galaxy": 35.0,
    "Gamepad": 47.5,
    "Garden Pot": 38.0,
    "Geisha Fan": 45.0,
    "Gem": 42.0,
    "Gift Box": 65.0,
    "Gift": 39.0,
    "Gingerbread": 39.0,
    "Glasses": 45.0,
    "Gold": 70.0,
    "Golden Scarab": 31.99,
    "Grape": 31.4,
    "Greek Helmet": 47.0,
    "Greek Sun": 35.0,
    "Griffon": 34.78,
    "Guitar": 28.5,
    "Handcuffs": 29.0,
    "Handset": 40.0,
    "Headband": 39.0,
    "Heart Balloon": 30.0,
    "Heart Box": 44.4,
    "Heart Lock": 39.87,
    "Hearts": 49.99,
    "Heraldic Lily": 39.0,
    "Hersir": 40.0,
    "High Heels": 33.0,
    "Hippo": 40.0,
    "Holy Grail": 35.95,
    "Horn": 51.0,
    "Horseshoe": 26.48,
    "Hot Matcha": 40.0,
    "Ice Cream": 129.0,
    "Ice Pop": 99.99,
    "Illuminati": 35.0,
    "Imperial Lion": 70.0,
    "Inguz Rune": 42.0,
    "Ink Pen": 74.0,
    "Jewel": 26.8,
    "Jolly Roger": 30.0,
    "Jörmungandr": 35.0,
    "Key": 28.69,
    "Khinkali": 35.0,
    "Kite": 35.0,
    "Kitsune": 95.0,
    "Knight": 39.5,
    "Koala": 69.9,
    "La Corona": 30.0,
    "Ladybug": 40.0,
    "Leaf": 150.0,
    "Lingerie": 32.5,
    "Lion Head": 88.0,
    "Lion King": 38.0,
    "Lion of Babylon": 45.0,
    "Lotus Flower": 150.0,
    "Love Bulb": 35.0,
    "Love Cherry": 28.0,
    "Love Letter": 33.5,
    "Love Lock": 25.97,
    "Love Mug": 36.0,
    "Love Potion": 38.5,
    "Love Puzzle": 35.0,
    "Love Scene": 39.99,
    "Loveberry": 140.0,
    "Lovebirds": 36.0,
    "Lovely Key": 28.0,
    "Lovely Kiss": 47.0,
    "Lovely Rose": 1995.0,
    "Lovestruck": 30.25,
    "Magic Vial": 63.0,
    "Mailbox": 45.0,
    "Mannaz Rune": 42.0,
    "Maple Leaf": 85.0,
    "Mars & Venus": 42.0,
    "Mask": 38.99,
    "Mayan Moth": 33.99,
    "Money Bag": 40.0,
    "Moon Cross": 35.0,
    "Moon": 31.0,
    "Morgenstern": 33.0,
    "Mountain Goat": 30.0,
    "Muffin": 29.59,
    "Mustache": 64.0,
    "Mustang": 118.0,
    "Narcissus": 28.88,
    "Neko Mask": 40.0,
    "Nemean Lion": 34.99,
    "Nordic Wolf": 29.99,
    "Novus Ordo": 40.0,
    "Oak Leaf": 31.0,
    "Oculus": 33.9,
    "Okami Wolf": 36.0,
    "Old Candle": 29.5,
    "Origami": 27.9,
    "Ouroboros": 29.8,
    "Owl": 36.5,
    "Palette": 55.0,
    "Panty": 40.0,
    "Paper Crane": 29.0,
    "Paper Lantern": 37.0,
    "Party Popper": 44.8,
    "Paw Print": 55.0,
    "Paw": 130.0,
    "PC Mouse": 50.0,
    "Pear": 150.0,
    "Pegasus": 50.54,
    "Pencil": 40.0,
    "Phoenix": 50.0,
    "Pigeon": 42.0,
    "Pineapple": 49.0,
    "Pirate Scull": 30.0,
    "Pizza Slice": 41.98,
    "Plume": 55.0,
    "Polar Bear": 33.0,
    "Porrige": 75.0,
    "Pumpkin Coach": 42.0,
    "Pyramid": 48.0,
    "Rabbit Mask": 39.27,
    "Radar": 132.0,
    "Rain Drop": 30.0,
    "Rhino Warrior": 40.0,
    "Ring": 42.2,
    "Romantic Cake": 42.0,
    "Rook": 40.0,
    "Rooster": 34.95,
    "Rose": 32.0,
    "Royal Crown": 27.0,
    "Sakura Flower": 30.9,
    "Sakura": 29.0,
    "Sauron": 29.0,
    "Scissors": 34.99,
    "Scorpion": 29.0,
    "Sea Dragon": 320.0,
    "Seahorse": 36.0,
    "Shell": 39.0,
    "Shield": 45.0,
    "Shinto Shrine": 35.0,
    "Shiny Heart": 39.0,
    "Shooting Star": 40.0,
    "Silver Ibis": 35.0,
    "Snail": 29.9,
    "Spades": 55.0,
    "Spider": 35.0,
    "Spirit Impala": 52.0,
    "Sprout": 96.0,
    "Star Crown": 29.9,
    "Star": 40.0,
    "Succubus": 48.0,
    "Sumerian Bird": 31.99,
    "Sunflower": 30.0,
    "Sweets Box": 26.85,
    "Sword Fight": 30.0,
    "Takoyaki": 58.0,
    "Tamagotchi": 28.88,
    "Teddy Bear": 63.0,
    "The Eye": 44.99,
    "Thief": 63.0,
    "Tie": 27.0,
    "Top Hat": 32.0,
    "Totem Bear": 44.67,
    "Tribal Shield": 33.0,
    "Trickster Fox": 27.0,
    "Trinity Knot": 45.0,
    "Trophy": 34.5,
    "Tsunami": 28.88,
    "Tulip": 34.99,
    "Turtle": 99.99,
    "Twin Koi": 40.0,
    "Two Hearts": 49.9,
    "Two Katanas": 32.49,
    "UFO": 45.0,
    "Unicorn Head": 40.0,
    "Valkyrie": 45.0,
    "Venetian Mask": 32.0,
    "Viking Shield": 40.0,
    "Viper": 49.0,
    "Vortex": 100.0,
    "Wagasa": 41.99,
    "War Tiger": 33.0,
    "Warhorse": 85.0,
    "Wasp": 31.0,
    "Water Drops": 42.0,
    "Watermelon": 35.0,
    "Wepwawet": 40.0,
    "White Deer": 28.0,
    "Wine Toast": 29.66,
    "Wise Raven": 31.99,
    "Wolf Rage": 30.4,
    "Worker Ant": 42.0,
    "Wreath": 28.8,
    "Yogi Shaman": 40.0
  },
  "models": {
    "Acid Green": 26.07,
    "Amethyst": 32.0,
    "Arabian Night": 30.0,
    "Aurora": 35.0,
    "Azurite": 35.0,
    "Barbie Gem": 29.8,
    "Black Amber": 26.5,
    "Black Hole": 50.0,
    "Black Thorn": 52.0,
    "Black Velvet": 26.45,
    "Blood Band": 30.0,
    "Blood Orange": 26.5,
    "Bloodstone": 44.0,
    "Blue Pearl": 27.0,
    "Bondi Blue": 26.65,
    "Bronze Heart": 25.99,
    "Bubble Burst": 39.9,
    "Canary": 26.15,
    "Champagne": 28.9,
    "Citrus Shift": 27.0,
    "Clam Shell": 30.0,
    "Cobalt Rose": 44.2,
    "Cold Desire": 45.0,
    "Cold Fusion": 36.21,
    "Color Blocks": 30.0,
    "Color Chaos": 29.0,
    "Color Spray": 40.0,
    "Copper Rose": 27.0,
    "Couture": 40.0,
    "Dark Orchid": 38.14,
    "Diamond": 59.0,
    "Doodle": 35.0,
    "Dorodango": 26.26,
    "Dragon Eyes": 30.0,
    "Eclipse": 35.0,
    "El Dorado": 27.0,
    "Elven Tears": 30.0,
    "Emerald": 30.0,
    "Fireball": 69.0,
    "Firestorm": 38.0,
    "Flamingo": 27.3,
    "Forest Lake": 29.5,
    "Freehand": 33.0,
    "Frostband": 29.0,
    "Glamour": 27.2,
    "Goldfinger": 43.5,
    "Graffiti": 80.0,
    "Honeydew": 29.99,
    "Hot Pink": 30.0,
    "Inferno": 33.5,
    "Iron Feather": 40.0,
    "Line Art": 48.0,
    "Manhattan": 39.0,
    "Marigold": 48.9,
    "Miami Beach": 35.0,
    "Midnight": 65.0,
    "Mikado Yellow": 25.98,
    "Mint Candy": 28.0,
    "Neon Chrome": 30.0,
    "Nightshade": 30.0,
    "Nocturne": 39.99,
    "Obsidian": 34.27,
    "Ocean Agate": 34.0,
    "Ocean Gem": 35.0,
    "Orion": 38.0,
    "Peridot": 27.0,
    "Pink Diamond": 60.0,
    "Pink Lover": 30.0,
    "Princess Cut": 27.0,
    "Prismatic": 26.89,
    "Pure Love": 55.55,
    "Quick Silver": 47.0,
    "Rainbow": 49.0,
    "Red Light": 26.34,
    "Red Velvet": 29.85,
    "Red Wedding": 30.0,
    "Rose Quartz": 32.0,
    "Royal Purple": 29.5,
    "Sapphire": 35.0,
    "Scrapyard": 29.9,
    "Silver Lake": 27.77,
    "Silver Smoke": 44.0,
    "Silver Star": 35.0,
    "Sketch": 33.0,
    "Snake Eye": 28.88,
    "Sovereign": 48.0,
    "Space Steel": 35.0,
    "Steampunk": 28.0,
    "Sunrise": 29.0,
    "Sunset": 33.33,
    "Tesla": 64.99,
    "Topaz": 27.5,
    "Twilight": 36.0,
    "Ultramarine": 27.0,
    "Valentine": 49.0,
    "Velvet Rose": 48.5,
    "Vice City": 32.0,
    "Vintage Glam": 36.0,
    "Water Lily": 26.5,
    "Whirlpool": 29.92
  },
  "last_updated": 1783048618
}