{
  "backdrops": {
    "Black": 17.15,
    "Chocolate": 2.5,
    "Strawberry": 2.54,
    "Dark Lilac": 2.56,
    "Emerald": 2.55,
    "Cappuccino": 2.55,
    "Carrot Juice": 2.53,
    "French Blue": 2.58,
    "Steel Grey": 2.58,
    "Pacific Green": 2.56,
    "Neon Blue": 2.49,
    "Turquoise": 2.54,
    "Pine Green": 2.49,
    "Roman Silver": 2.54,
    "Navy Blue": 2.58,
    "Platinum": 2.59,
    "Rosewood": 2.49,
    "Cobalt Blue": 2.59,
    "Shamrock Green": 2.57,
    "Moonstone": 2.57,
    "Cyberpunk": 2.59,
    "Light Olive": 2.53,
    "Pistachio": 2.54,
    "Aquamarine": 2.49,
    "Purple": 2.57,
    "Orange": 2.54,
    "Coral Red": 2.5,
    "Pure Gold": 2.57,
    "Amber": 2.56,
    "Indigo Dye": 2.55,
    "Midnight Blue": 4.35,
    "Electric Purple": 2.59,
    "Pacific Cyan": 2.54,
    "Sky Blue": 2.57,
    "Chestnut": 2.55,
    "Battleship Grey": 2.54,
    "Khaki Green": 2.51,
    "Ivory White": 2.6,
    "Satin Gold": 2.56,
    "Burgundy": 2.5,
    "Persimmon": 2.57,
    "Azure Blue": 2.57,
    "Lemongrass": 2.55,
    "Desert Sand": 2.59,
    "Hunter Green": 2.49,
    "Silver Blue": 2.58,
    "Malachite": 2.49,
    "English Violet": 2.51,
    "Mystic Pearl": 2.48,
    "Raspberry": 2.48,
    "Caramel": 2.51,
    "Electric Indigo": 2.53,
    "Grape": 2.55,
    "Copper": 2.54,
    "Sapphire": 2.58,
    "Fandango": 2.49,
    "Lavender": 2.57,
    "Jade Green": 2.5,
    "Mint Green": 2.56,
    "Onyx Black": 5.29
  },
  "symbols": {
    "Acorn": 4.49,
    "Alarm": 5.0,
    "Alkonost": 6.0,
    "Anchor": 4.5,
    "Apple": 5.0,
    "Arabian Horse": 4.5,
    "Avocado": 5.0,
    "Axe": 5.0,
    "Ball": 4.2,
    "Bandage": 6.0,
    "Baphomet": 4.8,
    "Bastet": 5.0,
    "Bee": 5.0,
    "Beetle": 5.15,
    "Bell Pepper": 3.83,
    "Birthday Cake": 5.0,
    "Bishop": 5.0,
    "Blood Drop": 5.5,
    "Boat": 5.0,
    "Bone": 4.02,
    "Book": 4.5,
    "Bottle": 5.0,
    "Bottlenose": 4.9,
    "Bow Tie": 3.98,
    "Brain": 6.0,
    "Bread": 4.2,
    "Bubble Tea": 4.12,
    "Bubbles": 4.3,
    "Bug": 5.0,
    "Bull of Heaven": 4.4,
    "Bunny Ears": 4.0,
    "Bunny": 5.43,
    "Burger": 4.9,
    "Cactus": 4.35,
    "Calm Wolf": 5.0,
    "Candle": 6.0,
    "Candy": 4.5,
    "Cap": 4.9,
    "Car": 4.0,
    "Carambola": 4.0,
    "Carrot": 4.0,
    "Cash": 4.5,
    "Cat Mask": 4.0,
    "Celtic Cross": 5.0,
    "Celtic Wolf": 4.79,
    "Champagne": 4.99,
    "Cheese": 5.0,
    "Cherry": 5.0,
    "Chest": 4.4,
    "Chili Pepper": 4.02,
    "Chili": 6.0,
    "Cicada": 5.45,
    "Clover": 4.9,
    "Clubs": 4.0,
    "Coat of Arms": 4.75,
    "Cobra": 4.5,
    "Cocktail": 4.99,
    "Coconut": 5.3,
    "Coffee Bean": 4.9,
    "Coin Purse": 6.0,
    "Coin": 6.0,
    "Conch": 5.0,
    "Cone": 4.0,
    "Corn": 3.62,
    "Crab": 5.1,
    "Croissant": 5.0,
    "Crown": 6.0,
    "Crusader": 4.0,
    "Crystal Ball": 4.0,
    "Cupcake": 5.2,
    "Cursor": 3.83,
    "Dessert": 4.0,
    "Diamond": 4.9,
    "Diamonds": 4.5,
    "Dice": 4.13,
    "Doberman": 5.0,
    "Dolphin": 5.0,
    "Dragonfly": 5.0,
    "Drug": 5.0,
    "Eagle": 4.19,
    "Eggplant": 4.02,
    "Eikthyrnir": 4.2,
    "Elephant": 4.5,
    "Feather": 4.49,
    "Fehu Rune": 5.0,
    "Fenrir": 6.0,
    "Fire": 3.74,
    "Firebird": 5.0,
    "Fish Skeleton": 4.99,
    "Fish": 4.9,
    "Flamingo": 4.0,
    "Flashlight": 6.0,
    "Fleur-de-lis": 4.2,
    "Flipper": 5.0,
    "Flower Cross": 4.0,
    "Flower Tulip": 5.5,
    "Flower": 4.7,
    "Gamepad": 4.0,
    "Garden Pot": 4.4,
    "Gear": 3.74,
    "Gem": 4.6,
    "Ghost": 5.0,
    "Gift Box": 5.0,
    "Gingerbread": 4.56,
    "Glasses": 4.99,
    "Gold": 4.99,
    "Golden Scarab": 4.85,
    "Grape": 5.0,
    "Grenade": 4.9,
    "Guitar": 4.38,
    "Hamburger": 4.0,
    "Hammerhead": 5.0,
    "Hand of God": 5.0,
    "Handset": 4.99,
    "Heart": 5.42,
    "Hedgehog": 4.13,
    "Hermit Shell": 4.0,
    "High Heels": 6.0,
    "Ice Pop": 4.2,
    "Illuminati": 4.34,
    "Inca Sun": 4.0,
    "Inguz Rune": 5.0,
    "Ink Pen": 4.0,
    "Jellyfish": 4.99,
    "Jumbo Pencil": 4.2,
    "Key": 4.5,
    "Kite": 4.35,
    "Kitsune": 4.29,
    "Knight": 6.0,
    "Koala": 5.0,
    "Ladybug": 4.29,
    "Leaf": 5.0,
    "Lemon Slice": 5.0,
    "Lemon": 4.0,
    "Light Bulb": 4.5,
    "Lightning": 3.88,
    "Like": 5.21,
    "Lily": 5.0,
    "Lion Head": 4.14,
    "Lion King": 4.99,
    "Love Letter": 5.0,
    "Love Lock": 4.39,
    "Lovely Kiss": 4.0,
    "Mafdet": 4.99,
    "Magic Wand": 4.3,
    "Mannaz Rune": 4.99,
    "Manta Ray": 5.0,
    "Maple Leaf": 6.0,
    "Maple": 4.95,
    "Mask": 5.0,
    "Mayan Moth": 4.9,
    "Melon": 4.35,
    "Money Bag": 6.0,
    "Monstera": 5.0,
    "Moon Cross": 6.0,
    "Moon": 4.4,
    "Moose Head": 5.0,
    "Mountain Goat": 4.99,
    "Mountain Lion": 4.4,
    "Mushroom": 4.99,
    "Musical Note": 6.0,
    "Narcissus": 5.21,
    "Nordic Wolf": 6.0,
    "Oak Leaf": 4.4,
    "Octopus": 5.0,
    "Okami Wolf": 4.0,
    "Ouroboros": 5.5,
    "Owl": 4.99,
    "Oxen of Fire": 4.5,
    "Palette": 4.5,
    "Paw": 5.0,
    "Pawn": 6.0,
    "PC Mouse": 4.5,
    "Pear": 5.0,
    "Pearl": 4.49,
    "Pegasus": 4.0,
    "Pencil": 5.0,
    "Phoenix": 4.0,
    "Pickaxe": 4.0,
    "Piggy Bank": 4.5,
    "Pineapple": 4.0,
    "Pizza Slice": 4.49,
    "Piñata": 4.99,
    "Planet": 4.99,
    "Plum": 4.1,
    "Plume": 5.0,
    "Polar Bear": 4.99,
    "Police Badge": 5.9,
    "Pomegranate": 5.9,
    "Potion": 5.0,
    "Pyramid": 4.19,
    "Rain Drop": 4.2,
    "Ram of Amun": 3.62,
    "Red Deer": 4.49,
    "Rhino Warrior": 4.8,
    "Ring": 6.0,
    "Rocket": 5.0,
    "Rook": 5.0,
    "Royal Crown": 4.0,
    "Sakura": 4.14,
    "Scarab": 5.0,
    "Scissors": 6.0,
    "Scorpion": 5.0,
    "Sea Horse": 4.1,
    "Sea Jelly": 4.1,
    "Seahorse": 5.0,
    "Shark Knife": 4.99,
    "Sharp Sword": 5.0,
    "Shell": 5.0,
    "Shield": 4.99,
    "Shooting Star": 4.56,
    "Skull": 3.97,
    "Smartphone": 4.0,
    "Spades": 4.9,
    "Spanner": 4.4,
    "Sparks": 3.73,
    "Spider Web": 3.7,
    "Spirit Impala": 6.0,
    "Sprout": 4.0,
    "Star Crown": 5.0,
    "Star": 6.0,
    "Strawberry": 5.0,
    "Sumerian Bird": 5.0,
    "Sun Lion": 4.99,
    "Sun Mountain": 4.5,
    "Sun": 5.0,
    "Sunflower": 4.35,
    "Sword": 4.2,
    "The Eye": 5.95,
    "Thief": 5.5,
    "Tie": 4.5,
    "Toilet Paper": 4.19,
    "Toilet": 3.98,
    "Tooth": 5.0,
    "Top Hat": 6.0,
    "Totem Bear": 4.02,
    "Toy Bucket": 4.5,
    "Tree of Life": 3.62,
    "Tribal Shield": 8.0,
    "Trophy": 5.0,
    "Tulip": 5.9,
    "Turkey": 4.25,
    "Turtle": 4.1,
    "Twin Peaks": 4.18,
    "UFO": 4.95,
    "Unicorn Head": 4.8,
    "Unicorn": 4.5,
    "Venetian Mask": 5.0,
    "Viking": 4.99,
    "Vortex": 4.5,
    "Wasp": 4.0,
    "Watermelon": 4.7,
    "White Deer": 4.0,
    "Wolf Rage": 4.0,
    "Wreath": 5.0,
    "Yogi Shaman": 6.0
  },
  "models": {
    "Anniversary": 4.04,
    "Backyard": 4.1,
    "Be Awesome!": 3.8,
    "Best Wishes": 3.9,
    "Black Ink": 4.2,
    "Blue Caramel": 4.08,
    "Bright Side": 4.16,
    "Broadway": 5.98,
    "Bronze Age": 4.15,
    "Bubbly": 6.0,
    "Candy Message": 4.19,
    "Cheers": 3.96,
    "Cherrific": 6.0,
    "Choco Wax": 4.5,
    "Citrus Candy": 4.16,
    "Confetti": 4.16,
    "Cotton Candy": 5.44,
    "Crazy Frog": 14.0,
    "Crunchy": 5.5,
    "Donut Cream": 4.3,
    "Dream Big": 4.8,
    "Duck Attack": 5.88,
    "Eggcellent": 5.6,
    "Eternal Glow": 4.5,
    "Festive Day": 4.49,
    "Festive": 4.08,
    "Final Boss": 9.0,
    "Firecracker": 5.9,
    "Forecast": 4.1,
    "Forever Young": 3.89,
    "Fresh Mint": 5.0,
    "Glitch": 6.0,
    "Glittery Day": 4.09,
    "Golden Age": 4.5,
    "Golden Hour": 3.97,
    "Happy Flame": 4.22,
    "Happy Meows": 14.0,
    "Ice Crackle": 4.36,
    "Icicle": 4.04,
    "Icy Pink": 4.25,
    "Jage Crystal": 4.4,
    "Jelly Bubble": 3.95,
    "Jelly Desert": 4.33,
    "Juicy Ginger": 4.35,
    "Kaboom!": 8.88,
    "Lolipop": 4.06,
    "Magic Powers": 3.91,
    "Melted Butter": 7.0,
    "Midnight": 4.5,
    "Moon Wish": 4.05,
    "Mouse Brunch": 6.48,
    "Multicolor": 3.96,
    "Neon Lights": 5.7,
    "Neon Sign": 4.4,
    "Old Cartoon": 4.84,
    "On Fire": 10.0,
    "Orange Mood": 4.36,
    "Party Hard": 4.05,
    "Pastel Spark": 4.9,
    "Payday": 7.58,
    "Peachy": 4.18,
    "Pear Cocktail": 4.03,
    "Pinky Dream": 3.99,
    "Pixel Wish": 5.87,
    "Poltergeist": 4.16,
    "Pop Art": 4.39,
    "Pop Tart": 4.19,
    "Princess": 4.94,
    "Purr Magic": 4.99,
    "Rainbow": 4.0,
    "Red Ribbon": 5.75,
    "Rose Mint": 4.3,
    "Shine Bright": 4.2,
    "Shine On": 4.8,
    "Shocker": 8.0,
    "Silver Year": 3.87,
    "Small Gifts": 5.1,
    "Sparkler": 4.5,
    "Spring Meadow": 4.5,
    "Stardust": 3.84,
    "Starry Night": 4.16,
    "Stay Cool": 5.5,
    "Steel Strong": 4.59,
    "Sugar Party": 3.85,
    "Summer Walk": 4.16,
    "Superstar": 4.0,
    "Sweet Glaze": 4.8,
    "Tender Flame": 4.04,
    "Tropic Dream": 4.19,
    "Tropicana": 4.18,
    "Twilight Beam": 4.04,
    "Valentine": 5.7,
    "Wait a Minute": 4.9,
    "Warm Wick": 4.19,
    "Wax Glow": 4.04,
    "Wee Hours": 3.89,
    "Wicked": 4.05,
    "Winter Fun": 6.0,
    "Winter Noon": 4.05,
    "You Rock!": 4.3
  },
  "last_updated": 1783083131
}