{
  "backdrops": {
    "Burgundy": 2.48,
    "Chestnut": 2.48,
    "English Violet": 2.49,
    "Sapphire": 2.5,
    "Grape": 2.49,
    "Platinum": 2.53,
    "Aquamarine": 2.49,
    "Indigo Dye": 2.49,
    "Shamrock Green": 2.48,
    "Purple": 2.49,
    "Navy Blue": 2.49,
    "Cappuccino": 2.48,
    "Azure Blue": 2.47,
    "Jade Green": 2.48,
    "Raspberry": 2.5,
    "Carrot Juice": 2.49,
    "Copper": 2.49,
    "Moonstone": 2.48,
    "Dark Lilac": 2.5,
    "Silver Blue": 2.49,
    "Pacific Cyan": 2.48,
    "Desert Sand": 2.48,
    "Electric Purple": 2.49,
    "French Blue": 2.49,
    "Neon Blue": 2.49,
    "Coral Red": 2.48,
    "Pine Green": 2.49,
    "Battleship Grey": 2.47,
    "Cyberpunk": 2.7,
    "Strawberry": 2.49,
    "Light Olive": 2.48,
    "Pistachio": 2.49,
    "Rosewood": 2.48,
    "Malachite": 2.49,
    "Caramel": 2.5,
    "Electric Indigo": 2.5,
    "Chocolate": 2.49,
    "Lavender": 2.46,
    "Lemongrass": 2.48,
    "Orange": 2.49,
    "Midnight Blue": 2.5,
    "Fandango": 2.49,
    "Steel Grey": 2.53,
    "Cobalt Blue": 2.49,
    "Emerald": 2.48,
    "Roman Silver": 2.49,
    "Satin Gold": 2.49,
    "Khaki Green": 2.48,
    "Ivory White": 2.48,
    "Sky Blue": 2.48,
    "Pacific Green": 2.49,
    "Mint Green": 2.49,
    "Pure Gold": 2.48,
    "Persimmon": 2.49,
    "Turquoise": 2.47,
    "Amber": 2.48,
    "Mystic Pearl": 2.48,
    "Hunter Green": 2.49,
    "Black": 45.0,
    "Onyx Black": 19.0
  },
  "symbols": {
    "Alarm": 12.0,
    "Alkonost": 21.77,
    "Amour Scoops": 16.56,
    "Anchor": 12.0,
    "Apple": 8.43,
    "Arabian Horse": 17.0,
    "Aubergine": 9.69,
    "Autumn Leaves": 15.0,
    "Ball": 99.99,
    "Baphomet": 8.68,
    "Beetle": 8.5,
    "Bell Pepper": 15.04,
    "Bishop": 15.31,
    "Black Widow": 15.5,
    "Blood Drop": 8.59,
    "Bloody Axe": 8.29,
    "Blossom": 15.0,
    "Boat": 16.25,
    "Bottle": 16.56,
    "Bottlenose": 19.98,
    "Bow Tie": 12.0,
    "Brain": 11.0,
    "Broken Heart": 14.74,
    "Bubbles": 10.5,
    "Bug": 18.45,
    "Bull of Heaven": 8.5,
    "Bunny Ears": 18.5,
    "Bunny": 21.0,
    "Butterfly": 16.2,
    "Cactus": 17.5,
    "Candle": 18.0,
    "Candy": 16.56,
    "Carambola": 20.0,
    "Cash": 18.45,
    "Cat Mask": 20.0,
    "Cauldron": 9.7,
    "Champagne": 9.83,
    "Cheese": 14.0,
    "Chest": 12.5,
    "Chili": 16.0,
    "Chocolate": 17.0,
    "Clubs": 55.55,
    "Coat of Arms": 15.31,
    "Cocktail": 16.56,
    "Coffee Bean": 17.0,
    "Coffin": 10.99,
    "Coin": 12.0,
    "Cone": 15.0,
    "Croissant": 12.75,
    "Crow": 8.58,
    "Crown": 40.0,
    "Crystal Ball": 8.65,
    "Cunning Fox": 13.0,
    "Cupcake": 13.5,
    "Cupid's Arrow": 13.0,
    "Cupid": 15.0,
    "Cupid’s Arrow": 13.0,
    "Cursor": 17.5,
    "Cute Bear": 16.0,
    "Dessert": 15.05,
    "Diamond": 15.0,
    "Diamonds": 50.0,
    "Dice": 12.0,
    "Doberman": 19.0,
    "Double Bed": 14.9,
    "Dragonfly": 16.56,
    "Drug": 21.0,
    "Eggplant": 11.99,
    "Evil Pumpkin": 13.0,
    "Eyeball": 8.57,
    "Feather": 21.0,
    "Fenrir": 17.0,
    "Fire": 11.5,
    "Fish Skeleton": 8.8,
    "Flamingo": 14.0,
    "Flashlight": 13.0,
    "Fleur-de-lis": 17.0,
    "Flirty Message": 15.0,
    "Flower Tulip": 15.0,
    "Flower": 15.0,
    "Fluffy Wolf": 8.64,
    "Flying Heart": 17.75,
    "Flying Witch": 17.0,
    "Ghost": 13.0,
    "Gift Box": 10.0,
    "Golden Scarab": 19.8,
    "Grape": 10.99,
    "Gravestone": 8.69,
    "Grim Reaper": 8.68,
    "Guitar": 12.0,
    "Half Moon": 9.98,
    "Hamburger": 14.0,
    "Happy Smile": 14.0,
    "Heart Balloon": 8.8,
    "Heart Shades": 15.0,
    "Heart": 10.2,
    "Heartbeat": 40.0,
    "High Heels": 15.0,
    "Hippo": 18.0,
    "Human Scull": 13.05,
    "Ice Pop": 8.54,
    "Illuminati": 8.42,
    "Jaws": 8.59,
    "Jumbo Pencil": 15.0,
    "Key": 16.0,
    "Kite": 16.25,
    "Kitty Cat": 14.0,
    "Knight": 15.5,
    "Ladybug": 10.0,
    "Lemon Slice": 16.56,
    "Lemon": 29.0,
    "Lightning": 16.25,
    "Like": 14.0,
    "Lily": 13.0,
    "Lingerie": 16.0,
    "Lips": 10.3,
    "Lollipop": 8.28,
    "Love Dove": 13.0,
    "Love Letter": 8.29,
    "Love Lock": 15.0,
    "Loveberry": 14.0,
    "Lovebirds": 14.0,
    "Lovely Bra": 29.0,
    "Lovely Key": 14.99,
    "Lovely Kiss": 17.0,
    "Lovely Rain": 9.84,
    "Lovely Rose": 8.54,
    "Magic Wand": 8.28,
    "Mannaz Rune": 12.25,
    "Maple Leaf": 8.58,
    "Maple": 9.0,
    "Mask": 15.3,
    "Melon": 20.0,
    "Moon": 15.0,
    "Musical Note": 14.0,
    "Napkins": 10.0,
    "Narcissus": 8.5,
    "Nice Ghost": 14.0,
    "Night Bats": 8.29,
    "Nordic Wolf": 8.57,
    "Oak Leaf": 13.5,
    "Okami Wolf": 20.0,
    "Ouroboros": 13.5,
    "Padlock": 11.5,
    "Palette": 14.5,
    "Passion Latte": 16.25,
    "Patched Heart": 25.5,
    "Paw": 11.99,
    "Pear": 12.04,
    "Pearl": 17.0,
    "Pickaxe": 12.99,
    "Piggy Bank": 16.1,
    "Pineapple": 9.0,
    "Piñata": 9.0,
    "Planet": 17.0,
    "Plum": 17.0,
    "Plume": 12.0,
    "Poison Drop": 9.97,
    "Polar Bear": 17.0,
    "Pomegranate": 14.93,
    "Potion": 13.0,
    "Pyramid": 17.0,
    "Rabbit": 16.0,
    "Rain Drop": 11.49,
    "Rhino Warrior": 18.45,
    "Ring": 1499.0,
    "Romantic Cake": 17.0,
    "Rook": 10.0,
    "Royal Crown": 20.0,
    "Sakura": 14.3,
    "Sauron": 17.5,
    "Scarab": 16.29,
    "Scarecrow": 15.0,
    "Scissors": 19.0,
    "Sea Horse": 15.2,
    "Severed Hand": 12.0,
    "Shark Knife": 17.5,
    "Shiny Heart": 15.0,
    "Shooting Star": 15.0,
    "Skull": 8.94,
    "Sparks": 15.8,
    "Spider Web": 10.99,
    "Spirit Impala": 14.0,
    "Spooky Cat": 8.69,
    "Star Crown": 10.0,
    "Stilettos": 16.56,
    "Strawberry": 8.57,
    "Sun Mountain": 16.25,
    "Sun": 29.5,
    "Sunflower": 15.31,
    "Sweets Box": 8.95,
    "Sword": 12.0,
    "The Eye": 12.5,
    "Tie": 21.5,
    "Toilet Paper": 16.0,
    "Tooth": 20.0,
    "Top Hat": 10.0,
    "Totem Bear": 15.0,
    "Treats": 16.25,
    "Tree of Life": 15.0,
    "Tulip": 13.0,
    "Turkey": 16.56,
    "Turtle": 14.5,
    "UFO": 20.0,
    "Venetian Mask": 16.0,
    "Voodoo Doll": 8.65,
    "Vortex": 16.25,
    "Water Drops": 11.0,
    "Watermelon": 8.84,
    "Witch's Hat": 8.31,
    "Witch’s Hat": 8.31,
    "Wolf Rage": 19.0,
    "Wreath": 14.49
  },
  "models": {
    "Azalea": 8.3,
    "Black Cat": 90.0,
    "Black Dahlia": 12.0,
    "Blue Bull": 10.49,
    "Blue Iris": 8.63,
    "Calavera": 25.0,
    "Carnation": 9.03375,
    "Chromium": 22.5,
    "Citrus Twist": 8.3,
    "Cobweb": 11.0,
    "Cocoon": 40.0,
    "Daisy": 9.615375,
    "Dark Carnival": 50.0,
    "Dewdrop": 8.3,
    "Early Green": 8.3,
    "Frozen Violet": 8.19,
    "Ghost Rider": 25.0,
    "Glowing Goth": 8.6,
    "Gothic": 9.98,
    "Graffiti": 8.68,
    "Health Risk": 16.24,
    "Hypercolor": 9.4,
    "Jack Sparrow": 9.4,
    "Joyful Duck": 19.0,
    "Leopard": 33.0,
    "Luau Lily": 8.3,
    "Marigold": 9.9,
    "Mystic": 8.99,
    "Neon Green": 11.5,
    "Neon Pink": 8.9,
    "Newspaper": 15.0,
    "Nightshade": 8.3,
    "Pamplona": 9.0,
    "Peony": 8.9,
    "Pink Caprice": 8.2,
    "Poinsettia": 8.3,
    "Princess": 15.0,
    "Royal Azure": 8.42,
    "Sand Goldbud": 30.0,
    "Secret Sprout": 10.0,
    "Silversage": 8.5,
    "Soft Puff": 10.0,
    "Sun Dazzle": 8.58,
    "Sunburst": 8.3,
    "Sunset": 8.49,
    "Technicolor": 9.9,
    "Tim Burton": 19.99,
    "Vector": 11.0,
    "White Rose": 8.76,
    "Wreath": 8.25
  },
  "last_updated": 1781988138
}