{
  "backdrops": {
    "Desert Sand": 2.49,
    "Dark Green": 2.5,
    "Fandango": 2.59,
    "Old Gold": 2.5,
    "French Violet": 2.5,
    "Burnt Sienna": 2.51,
    "Pacific Cyan": 2.5,
    "Roman Silver": 2.5,
    "Carrot Juice": 2.5,
    "Navy Blue": 2.5,
    "Shamrock Green": 2.5,
    "Cappuccino": 2.5,
    "Indigo Dye": 2.48,
    "Seal Brown": 2.5,
    "Satin Gold": 2.51,
    "Steel Grey": 2.51,
    "Mystic Pearl": 2.5,
    "Jade Green": 2.5,
    "Electric Purple": 2.5,
    "Azure Blue": 2.5,
    "Midnight Blue": 15.0,
    "Feldgrau": 2.5,
    "Sky Blue": 2.49,
    "Rosewood": 2.49,
    "English Violet": 2.49,
    "Pacific Green": 2.49,
    "Lavender": 2.49,
    "Deep Cyan": 2.5,
    "Pine Green": 2.5,
    "Persimmon": 2.49,
    "Coral Red": 2.5,
    "Orange": 2.5,
    "Burgundy": 2.5,
    "Cyberpunk": 2.5,
    "Chocolate": 2.5,
    "Dark Lilac": 2.5,
    "Ranger Green": 2.49,
    "Tactical Pine": 2.5,
    "Gunmetal": 2.6,
    "Silver Blue": 2.49,
    "Aquamarine": 2.49,
    "Chestnut": 2.5,
    "Khaki Green": 2.5,
    "Mint Green": 2.5,
    "Strawberry": 2.49,
    "French Blue": 2.5,
    "Carmine": 2.52,
    "Copper": 2.5,
    "Grape": 2.5,
    "Rifle Green": 2.48,
    "Neon Blue": 2.5,
    "Platinum": 2.52,
    "Light Olive": 2.49,
    "Electric Indigo": 2.5,
    "Emerald": 2.49,
    "Pure Gold": 2.5,
    "Pistachio": 2.51,
    "Mexican Pink": 2.5,
    "Caramel": 2.5,
    "Hunter Green": 2.5,
    "Mustard": 2.49,
    "Tomato": 2.5,
    "Battleship Grey": 2.49,
    "Ivory White": 2.55,
    "Camo Green": 2.5,
    "Celtic Blue": 2.5,
    "Lemongrass": 2.49,
    "Amber": 2.5,
    "Malachite": 2.5,
    "Marine Blue": 2.5,
    "Purple": 2.5,
    "Cobalt Blue": 2.5,
    "Turquoise": 2.49,
    "Moonstone": 2.5,
    "Raspberry": 2.51,
    "Fire Engine": 2.5,
    "Sapphire": 2.49,
    "Gunship Green": 2.5,
    "Black": 84.84,
    "Onyx Black": 17.99
  },
  "symbols": {
    "Academic Cap": 7.94,
    "Acorn": 7.59,
    "Alert Serpent": 7.22,
    "All-Seeing Eye": 7.24,
    "Anchor": 7.15,
    "Anubis": 7.14,
    "Avocado": 10.0,
    "Axe": 8.99,
    "Aztec Totem": 7.94,
    "Baby Bottle": 8.14,
    "Ball": 7.4,
    "Bamboo": 7.14,
    "Banana": 7.98,
    "Banner": 7.77,
    "Bascinet": 7.14,
    "Bastet": 12.9,
    "Battle Axe": 7.7,
    "Beanie": 7.14,
    "Bearskin": 14.6,
    "Beer": 11.95,
    "Bell Pepper": 15.0,
    "Beret": 7.94,
    "Bike Helmet": 10.0,
    "Birthday Cake": 7.4,
    "Bishop": 7.15,
    "Bone": 8.85,
    "Bonsai": 9.0,
    "Bow Tie": 19.0,
    "Bowler Hat": 8.99,
    "Bread": 15.0,
    "Breeze": 7.35,
    "Bubble Tea": 7.94,
    "Bucket Hat": 8.5,
    "Bug": 7.5,
    "Bull of Heaven": 7.22,
    "Burger": 13.3,
    "Cactus": 9.0,
    "Calm Wolf": 7.15,
    "Candle": 7.14,
    "Candy": 13.0,
    "Car": 7.14,
    "Cash": 7.5,
    "Cavalier Hat": 7.1,
    "Celtic Wolf": 7.14,
    "Champagne": 7.7,
    "Chef Hat": 7.15,
    "Cherry": 7.14,
    "Chick": 7.23,
    "Chili Pepper": 11.9,
    "Chili": 7.34,
    "Clover": 7.12,
    "Coat of Arms": 7.14,
    "Cocktail": 7.6,
    "Coin Purse": 15.4,
    "Coin": 7.15,
    "Conch": 12.9,
    "Cone": 9.0,
    "Conical Hat": 8.4,
    "Corn": 12.49,
    "Cow Skull": 7.94,
    "Crab": 7.4,
    "Crescent": 9.9,
    "Croissant": 8.45,
    "Crown": 7.4,
    "Crusader Cross": 7.14,
    "Crusader": 8.3,
    "Cupcake": 8.0,
    "Dagger": 7.5,
    "Dessert": 16.8,
    "Diamonds": 7.14,
    "Double Axe": 7.14,
    "Dragonfly": 7.14,
    "Drug": 7.4,
    "Duck Face": 8.4,
    "Eagle": 7.14,
    "Earflap Hat": 7.14,
    "Earth": 8.0,
    "Egg": 7.14,
    "Eggplant": 7.14,
    "Fehu Rune": 7.35,
    "Firebird": 11.9,
    "Fireman Hat": 7.77,
    "Fish": 8.1,
    "Flashlight": 7.35,
    "Fleur-de-lis": 7.6,
    "Flower Cross": 7.14,
    "Flower Sun": 7.15,
    "Flower Tulip": 11.9,
    "Flower": 7.14,
    "Flying Dragon": 12.5,
    "Galaxy": 12.0,
    "Garden Pot": 9.7,
    "Gem": 7.34,
    "Ghost": 16.1,
    "Gift Box": 7.14,
    "Golden Scarab": 7.14,
    "Grape": 14.8,
    "Greek Helmet": 7.94,
    "Greek Sun": 9.5,
    "Grenade": 12.86,
    "Gua Pi Mao": 8.99,
    "Hamburger": 12.0,
    "Hammerhead": 11.9,
    "Hard Hat": 7.92,
    "Hazelnut": 7.14,
    "Heart": 7.4,
    "Heater Shield": 7.94,
    "Heraldic Lily": 12.98,
    "Hermit Shell": 7.94,
    "High Heels": 7.14,
    "Hippo": 7.15,
    "Holy Grail": 7.14,
    "Horn": 12.5,
    "Hourglass": 8.8,
    "Ice Cream": 8.9,
    "Inca Sun": 7.14,
    "Jellyfish": 15.0,
    "Keffiyeh": 13.0,
    "Khinkali": 14.0,
    "Kite": 9.99,
    "Kitsune Mask": 7.15,
    "Kitsune": 7.06,
    "Koala": 11.0,
    "Legionary": 19.0,
    "Lemon Slice": 10.85,
    "Lemon": 8.74,
    "Light Bulb": 8.9,
    "Like": 7.21,
    "Lily": 8.5,
    "Lion Head": 8.6,
    "Lion of Babylon": 13.6,
    "Love Letter": 8.0,
    "Love Lock": 9.0,
    "Lovely Kiss": 13.0,
    "Magic Vial": 7.14,
    "Magic Wand": 7.4,
    "Maple Leaf": 8.9,
    "Maple": 13.6,
    "Mask": 7.07,
    "Melon": 7.15,
    "Mining Helmet": 10.0,
    "Moai Head": 7.35,
    "Monstera": 7.1,
    "Moon Face": 7.59,
    "Moose Head": 9.99,
    "Mountain Goat": 9.98,
    "Mountain Lion": 14.0,
    "Mushroom": 10.0,
    "Musical Note": 7.15,
    "Mustache": 8.66,
    "Nemes": 7.15,
    "Nigiri": 10.94,
    "Nordic Wolf": 14.9,
    "Novus Ordo": 15.0,
    "Oak Leaf": 8.4,
    "Obon Lantern": 7.94,
    "Oculus": 7.1,
    "Old Candle": 7.4,
    "Omusubi": 12.5,
    "Onigiri": 10.0,
    "Origami": 7.14,
    "Ouroboros": 8.0,
    "Palette": 7.14,
    "Paper Crane": 7.4,
    "Party Hat": 7.7,
    "Paw": 25.0,
    "PC Mouse": 7.99,
    "Pear": 13.0,
    "Phoenix": 7.14,
    "Pickaxe": 7.94,
    "Piggy Bank": 21.0,
    "Pilot Hat": 7.14,
    "Pineapple": 13.0,
    "Pirate Hat": 7.95,
    "Planet": 8.8,
    "Plume Shako": 7.34,
    "Plume": 7.95,
    "Police Badge": 9.99,
    "Police Hat": 7.6,
    "Pomegranate": 8.69,
    "Potion": 12.3,
    "Press Hat": 8.77,
    "Puzzle": 13.5,
    "Radar": 13.7,
    "Ribeye Steak": 9.99,
    "Ring": 7.18,
    "Rook": 7.14,
    "Rose": 8.29,
    "Royal Crown": 7.14,
    "Sailor Hat": 7.06,
    "Sakura": 35.0,
    "Scarab": 7.14,
    "Scissors": 9.0,
    "Scorpion": 7.4,
    "Sea Dragon": 7.14,
    "Sea Horse": 7.36,
    "Sea Jelly": 8.3,
    "Seahorse": 7.14,
    "Serpent": 7.4,
    "Shark Knife": 13.0,
    "Shell": 15.0,
    "Shortsword": 7.24,
    "Shuriken": 13.0,
    "Smartphone": 7.42,
    "Spanner": 8.88,
    "Spellbook": 8.47,
    "Spider Web": 8.39,
    "Spirit Impala": 7.4,
    "Star Crown": 29.0,
    "Steampunk Hat": 7.15,
    "Strawberry": 9.0,
    "Sumerian Bird": 7.14,
    "Sun Lion": 7.14,
    "Sun Mountain": 8.0,
    "Sun": 8.0,
    "Sunflower": 7.14,
    "Sword Fight": 7.35,
    "Sword": 10.0,
    "Telescope": 7.5,
    "Tetsubin": 12.99,
    "Thor Hammer": 8.5,
    "Thunderbird": 8.3,
    "Tie": 8.5,
    "Tiki Mask": 7.14,
    "Toilet Paper": 7.14,
    "Tooth": 8.0,
    "Toy Bucket": 7.25,
    "Tree of Life": 8.0,
    "Tribal Shield": 7.15,
    "Tricorne": 7.94,
    "Trinity Knot": 9.97,
    "Tsunami": 8.88,
    "Tulip": 7.6,
    "Turban": 7.35,
    "Turkey": 9.5,
    "Turtle": 7.37,
    "Twin Koi": 9.29,
    "Twin Peaks": 7.14,
    "UFO": 13.0,
    "Unicorn Head": 7.24,
    "Ushanka": 9.15,
    "Valkyrie": 7.22,
    "Viking Shield": 7.14,
    "Viper": 14.0,
    "Vortex": 7.14,
    "War Bonnet": 7.4,
    "Warhorse": 7.14,
    "Wasp": 12.3,
    "Watching Sun": 7.3,
    "White Deer": 18.0,
    "Winged Helm": 7.14,
    "Winged Helmet": 9.7,
    "Wolf Rage": 13.0,
    "Worker Ant": 7.15,
    "Wreath": 13.0,
    "Yogi Shaman": 8.5
  },
  "models": {
    "Aetheris": 10.0,
    "Allamanda": 8.0,
    "Anemone": 8.29,
    "Aster": 11.95,
    "Aubrieta": 7.8,
    "Aurivelle": 7.31,
    "Azure": 9.0,
    "Barbia": 8.5,
    "Big Bang": 10.9,
    "Blazing Dusk": 14.5,
    "Bronzula": 9.9,
    "Brunnera": 15.0,
    "Bubblia": 34.5,
    "Bull's Eye": 24.9,
    "Bumblebee": 7.53,
    "Carnation": 24.15,
    "Celestara": 10.0,
    "Clivia": 8.0,
    "Cosmea": 8.9,
    "Crimsonia": 8.1,
    "Dahlia": 7.87,
    "Dark Loader": 14.99,
    "Dark Neo": 17.0,
    "Dog Flower": 65.0,
    "Eclipsia": 8.39,
    "Fabulous": 7.37,
    "False Bird": 7.39,
    "Fire Bloom": 10.25,
    "Flameris": 7.38,
    "Floravelle": 7.28,
    "Floraven": 7.23,
    "Floris": 7.31,
    "Flowey": 420.0,
    "Geranium": 9.0,
    "Gerbera": 7.57,
    "Ghostia": 10.0,
    "Glitch": 12.28,
    "Goldensia": 13.0,
    "Hawaii": 8.4,
    "Heartbeat": 14.99,
    "Hellebore": 7.4,
    "Hibiscus": 7.56,
    "Hollyhock": 9.49,
    "Hybrid": 8.2,
    "Hydrangea": 7.86,
    "Icebound": 19.0,
    "Indigo": 7.69,
    "Jellybud": 7.84,
    "Lanceolata": 8.2,
    "Lemon Queen": 7.52,
    "Loves Or Not": 31.8,
    "Luminosia": 12.0,
    "Lunaris": 8.3,
    "Marigold": 7.37,
    "Meadowlyn": 7.62,
    "Meower": 53.0,
    "Monsoon": 12.5,
    "Morning Sun": 13.0,
    "Myrtella": 16.0,
    "Nectarium": 7.29,
    "Nightshade": 14.0,
    "Noctivis": 7.83,
    "Orchidra": 7.23,
    "Oxalis": 7.23,
    "Party Bloom": 13.5,
    "Party Time": 9.43,
    "Peach Perfect": 9.0,
    "Peony": 16.9,
    "Petunia": 7.53,
    "Ping Blossom": 13.0,
    "Pixel Bloom": 14.5,
    "Plumeria": 11.0,
    "Pokerface": 9.34,
    "Primrose": 7.39,
    "Red Poppy": 7.97,
    "Sakura": 29.99,
    "Savanna": 9.9,
    "Seraphina": 7.23,
    "Shake It": 45.0,
    "Shimeria": 18.0,
    "Silveria": 9.3,
    "Snowdrop": 15.0,
    "Solivine": 8.0,
    "Spotty Leo": 14.0,
    "Sunflower": 43.0,
    "Sylvaris": 8.88,
    "Tropicana": 7.23,
    "Twilight": 7.77,
    "Vanilla": 7.5,
    "Venus Flytrap": 15.1,
    "Verdania": 7.39,
    "Violet Iris": 7.81,
    "Violet": 8.4,
    "White Peony": 10.4,
    "Wildflower": 10.5,
    "Wilted": 17.4,
    "Windy": 13.0,
    "Yellow Poppy": 9.9,
    "Zap Aster": 23.9,
    "Zephyra": 10.99,
    "Bull’s Eye": 29.99
  },
  "last_updated": 1782669853
}